foffinf/__init__.py
foffinf-0.1.dist-info/LICENSE
foffinf-0.1.dist-info/METADATA
foffinf-0.1.dist-info/WHEEL
foffinf-0.1.dist-info/top_level.txt
foffinf-0.1.dist-info/RECORD
