Metadata-Version: 2.1
Name: foffinf
Version: 0.1
Summary: A way to use stdlib's logging with the new Format Specification Mini-Language.
Home-page: https://github.com/facundobatista/foffinf
Author: Facundo Batista
Author-email: facundo@taniquetil.com.ar
License: GPL-v3
Platform: UNKNOWN
Classifier: License :: OSI Approved :: GNU General Public License v3 (GPLv3)
Classifier: Operating System :: OS Independent
Classifier: Programming Language :: Python :: 3
Requires-Python: >=3
License-File: LICENSE
